Workbook

Sheet 01_Project_Charter
A1: Project Aion — Project Charter & Intake
A2: Fill these in once; we’ll keep them updated as the single source of truth.
A3: Field | B3: Notes
A4: Project vision (1–2 sentences) | B4: Aion Global (Equine & Sport) will be a 50/50 collaboration between me (Shane Clarke) and my business partner Ned Sangster to compile our collective knowledge and resources to create a next generation global thoroughbred racing trading & performance measurement ecosystem. 1) Strategic Intent Purpose: Develop Project Aion into a repeatable, auditable trading capability that can be (a) commercialised as a standalone business or (b) integrated into a partner fund structure with external bankroll. 2) Two Commercialisation Pathways Path A — New Business: Own capital (initially) + build track record + scale capital later Outputs: productised stack, operations, risk controls, reporting Path B — Fund Collaboration / Bankroll Partner: Partner supplies capital; you supply edge + system + execution Outputs: institutional-grade reporting, risk policy, model governance, controls, and a due diligence pack 3) A “Decision Gate” (make it explicit) Add a milestone like: Decision Gate (end of Q3 2026): Choose Path A or Path B based on: live/sim performance vs targets operational readiness (controls + reliability) partner appetite / pipeline legal + compliance feasibility
A5: Primary objectives (top 5) | B5: Consolidatie Database Platform, Advanced Proprietary Data Operation, Develop initial phase routine daily Hidden Merit manual trading list for France & Hong Kong, Develop Modelling & Automated Trading platforms (with Chatgpt assitance)
A6: Non‑negotiable principles | B6: Data Integrity, Precision, Flexibility, Adaptation
A7: Scope: in / out
A8: Target markets & instruments | B8: France, Hong Kong, Japan, Australia, GCC
A9: Time horizons (early/mid/late, pre‑race/in‑play, etc.)
A10: Key resources (data, infra, tools, people) | B10: Sri Lanka Video Analysts BPO - Proprietary Data Compilation, Aion Global Database System, Advanced ML Feature Library, XGBoost Modelling Platform, Automated Full Market Spectrum (Tote, Fixed Odds, Betfair Exchange, Asian Exchange , Fixed Odds)
A11: Industry network / partnerships (optional)
A12: Constraints (legal/compliance, latency, costs, etc.) | B12: Phased development with development budget driven by trading revenue
A13: Success metrics (KPIs)
A14: Major risks & mitigations
A15: Open questions / decisions needed

Sheet 02_Roadmap
A1: High‑Level Roadmap (Epics)
A2: Baseline created: 2026-01-23 | Adjust dates/owners freely.
A4: Epic ID | B4: Epic | C4: Goal | D4: Owner | E4: Start | F4: End | G4: Duration (days) | H4: Status | I4: Dependency | J4: Notes
A5: E01 | B5: Foundation & governance | C5: Charter, structure, decision log, workflows | D5: You | E5: Q1_2026 | F5: Q1_2026 | G5: 15 | H5: Not started | J5: Sets up operating rhythm
A6: E02 | B6: Databases core | C6: Fundamental/Technical/Transactional domains + schemas | D6: TBD | E6: Q1_2026 | F6: Q2_2026 | G6: 60 | H6: Not started | I6: E01
A7: E03 | B7: Feature system | C7: Feature principles, profile, performance, ratings suite | D7: TBD | E7: Q1_2026 | F7: Q2_2026 | G7: 90 | H7: Not started | I7: E02 | J7: POWRTG/SPDRTG/MRKRTG/TRKSPD/Time Standards
A8: E04 | B8: ML & MLOps | C8: XGBoost module + MLflow + monitoring + gates | D8: TBD | E8: Q1_2026 | F8: Q2_2026 | G8: 90 | H8: Not started | I8: E03
A9: E05 | B9: Trading engines | C9: OMS/execution/risk guardrails/sim | D9: TBD | E9: Q2_2026 | F9: Q3_2026 | G9: 90 | H9: Not started | I9: E02
A10: E06 | B10: Pulse & triggers | C10: Race status, bet triggers, GUI pulse input | D10: TBD | E10: Q2_2026 | F10: Q3_2026 | G10: 90 | H10: Not started | I10: E02
A11: E07 | B11: Strategy library | C11: Early/Mid/Late, Tote, Exchange, Fixed Odds, Dividend, cA, Staking | D11: TBD | E11: Q2_2026 | F11: Q3_2026 | G11: 90 | H11: Not started | I11: E05
A12: E08 | B12: GUI Glass Cockpit | C12: Dash UI, design system, panels, icon library | D12: TBD | E12: Q2_2026 | F12: Q3_2026 | G12: 90 | H12: Not started | I12: E01
A13: E09 | B13: AWACS admin | C13: Monitoring, kill switches, permissions, drills | D13: TBD | E13: Q3_2026 | F13: Q3_2026 | G13: 90 | H13: Not started | I13: E05
A14: E10 | B14: BI / Reporting / Recon | C14: KPI layer, reporting packs, reconciliation controls | D14: TBD | E14: Q3_2026 | F14: Q4_2026 | G14: 120 | H14: Not started | I14: E02
A15: E11 | B15: Simulation & backtesting | C15: Deterministic replay + exec sim + review packs | D15: TBD | E15: Q3_2026 | F15: Q4_2026 | G15: 120 | H15: Not started | I15: E03
A16: E12 | B16: IT Infrastructure | C16: Envs, CI/CD, observability, security | D16: TBD | E16: Q1_2026 | F16: Q4_2026 | G16: 180 | H16: Not started | I16: E01 | J16: Parallel stream

Sheet 03_Gantt
A1: Gantt Chart (High‑Level Epics)
A2: Edit dates/status in 02_Roadmap. This sheet visualises automatically.
A4: Epic ID | B4: Epic | C4: Owner | D4: Start | E4: End | F4: Status | G4: 46045 | H4: 46052 | I4: 46059 | J4: 46066 | K4: 46073 | L4: 46080 | M4: 46087 | N4: 46094 | O4: 46101 | P4: 46108 | Q4: 46115 | R4: 46122 | S4: 46129 | T4: 46136 | U4: 46143 | V4: 46150 | W4: 46157 | X4: 46164 | Y4: 46171 | Z4: 46178 | AA4: 46185 | AB4: 46192 | AC4: 46199 | AD4: 46206 | AE4: 46213 | AF4: 46220
A5: ='02_Roadmap'!A5 | B5: ='02_Roadmap'!B5 | C5: ='02_Roadmap'!D5 | D5: Q1_2026 | E5: Q1_2026 | F5: ='02_Roadmap'!H5
A6: ='02_Roadmap'!A6 | B6: ='02_Roadmap'!B6 | C6: ='02_Roadmap'!D6 | D6: Q1_2026 | E6: Q2_2026 | F6: ='02_Roadmap'!H6
A7: ='02_Roadmap'!A7 | B7: ='02_Roadmap'!B7 | C7: ='02_Roadmap'!D7 | D7: Q1_2026 | E7: Q2_2026 | F7: ='02_Roadmap'!H7
A8: ='02_Roadmap'!A8 | B8: ='02_Roadmap'!B8 | C8: ='02_Roadmap'!D8 | D8: Q1_2026 | E8: Q2_2026 | F8: ='02_Roadmap'!H8
A9: ='02_Roadmap'!A9 | B9: ='02_Roadmap'!B9 | C9: ='02_Roadmap'!D9 | D9: Q2_2026 | E9: Q3_2026 | F9: ='02_Roadmap'!H9
A10: ='02_Roadmap'!A10 | B10: ='02_Roadmap'!B10 | C10: ='02_Roadmap'!D10 | D10: Q2_2026 | E10: Q3_2026 | F10: ='02_Roadmap'!H10
A11: ='02_Roadmap'!A11 | B11: ='02_Roadmap'!B11 | C11: ='02_Roadmap'!D11 | D11: Q2_2026 | E11: Q3_2026 | F11: ='02_Roadmap'!H11
A12: ='02_Roadmap'!A12 | B12: ='02_Roadmap'!B12 | C12: ='02_Roadmap'!D12 | D12: Q2_2026 | E12: Q3_2026 | F12: ='02_Roadmap'!H12
A13: ='02_Roadmap'!A13 | B13: ='02_Roadmap'!B13 | C13: ='02_Roadmap'!D13 | D13: Q3_2026 | E13: Q3_2026 | F13: ='02_Roadmap'!H13
A14: ='02_Roadmap'!A14 | B14: ='02_Roadmap'!B14 | C14: ='02_Roadmap'!D14 | D14: Q3_2026 | E14: Q4_2026 | F14: ='02_Roadmap'!H14
A15: ='02_Roadmap'!A15 | B15: ='02_Roadmap'!B15 | C15: ='02_Roadmap'!D15 | D15: Q3_2026 | E15: Q4_2026 | F15: ='02_Roadmap'!H15
A16: ='02_Roadmap'!A16 | B16: ='02_Roadmap'!B16 | C16: ='02_Roadmap'!D16 | D16: Q1_2026 | E16: Q4_2026 | F16: ='02_Roadmap'!H16

Sheet 04_Tickets
A1: Ticketing System (Backlog)
A2: Use this as a lightweight Jira: each row is a ticket. Filter/sort freely.
A4: Ticket ID | B4: Epic | C4: Component | D4: Type | E4: Summary | F4: Priority | G4: Status | H4: Owner | I4: Estimate (hrs) | J4: Start | K4: Due | L4: Dependencies | M4: Acceptance Criteria | N4: Created | O4: Updated | P4: Notes/Link | Q4: Realm | R4: Framework_Path | S4: Roadmap_Milestone
A5: T-0001 | B5: E01 | C5: Project Foundation | D5: Task | E5: Finalize project charter + principles | F5: P1 | G5: In progress | H5: You | I5: 6 | J5: 46045 | K5: 46048 | M5: Charter filled + agreed | N5: 46045 | O5: 46045 | Q5: 00_Triage_Inbox | R5: Project_Aion/00_Triage_Inbox | S5: TRIAGE
A6: T-0002 | B6: E02 | C6: 07_Databases | D6: Epic | E6: Define canonical entity IDs + mappings | F6: P1 | G6: Not started | H6: TBD | I6: 12 | J6: 46052 | K6: 46066 | L6: T-0001 | M6: IDs documented + mapping rules | N6: 46045 | O6: 46045 | Q6: 00_Triage_Inbox | R6: Project_Aion/00_Triage_Inbox | S6: TRIAGE
A7: T-0003 | B7: E03 | C7: Features_Profile | D7: Task | E7: Create feature spec template + catalog index | F7: P1 | G7: Not started | H7: TBD | I7: 8 | J7: 46059 | K7: 46073 | L7: T-0001 | M7: Template + example spec complete | N7: 46045 | O7: 46045 | Q7: 00_Triage_Inbox | R7: Project_Aion/00_Triage_Inbox | S7: TRIAGE
A8: T-0004 | B8: E08 | C8: GUI_Glass_Cockpit | D8: Task | E8: Define cockpit screen map + key panels | F8: P2 | G8: Not started | H8: TBD | I8: 10 | J8: 46066 | K8: 46080 | L8: T-0001 | M8: Screen map + panel list | N8: 46045 | O8: 46045 | Q8: 00_Triage_Inbox | R8: Project_Aion/00_Triage_Inbox | S8: TRIAGE
A9: T-0005 | B9: E11 | C9: Backtesting | D9: Task | E9: Decide replay granularity + event-time rules | F9: P1 | G9: Not started | H9: TBD | I9: 6 | J9: 46066 | K9: 46077 | L9: T-0002 | M9: Rules doc complete | N9: 46045 | O9: 46045 | Q9: 00_Triage_Inbox | R9: Project_Aion/00_Triage_Inbox | S9: TRIAGE

Sheet 05_Dashboard
A1: Dashboard (Auto)
A2: Counts update as you add/edit tickets.
A4: Ticket counts by Status | D4: Ticket counts by Priority
A6: Status | B6: Count | D6: Priority | E6: Count
A7: Backlog | B7: =COUNTIF('04_Tickets'!$G:$G,"Backlog") | D7: P0 | E7: =COUNTIF('04_Tickets'!$F:$F,"P0")
A8: Not started | B8: =COUNTIF('04_Tickets'!$G:$G,"Not started") | D8: P1 | E8: =COUNTIF('04_Tickets'!$F:$F,"P1")
A9: In progress | B9: =COUNTIF('04_Tickets'!$G:$G,"In progress") | D9: P2 | E9: =COUNTIF('04_Tickets'!$F:$F,"P2")
A10: Blocked | B10: =COUNTIF('04_Tickets'!$G:$G,"Blocked") | D10: P3 | E10: =COUNTIF('04_Tickets'!$F:$F,"P3")
A11: Ready for review | B11: =COUNTIF('04_Tickets'!$G:$G,"Ready for review")
A12: Done | B12: =COUNTIF('04_Tickets'!$G:$G,"Done")
A14: Epics status snapshot
A16: Epic | B16: Status | C16: Start | D16: End
A17: ='02_Roadmap'!B5 | B17: ='02_Roadmap'!H5 | C17: ='02_Roadmap'!E5 | D17: ='02_Roadmap'!F5
A18: ='02_Roadmap'!B6 | B18: ='02_Roadmap'!H6 | C18: ='02_Roadmap'!E6 | D18: ='02_Roadmap'!F6
A19: ='02_Roadmap'!B7 | B19: ='02_Roadmap'!H7 | C19: ='02_Roadmap'!E7 | D19: ='02_Roadmap'!F7
A20: ='02_Roadmap'!B8 | B20: ='02_Roadmap'!H8 | C20: ='02_Roadmap'!E8 | D20: ='02_Roadmap'!F8
A21: ='02_Roadmap'!B9 | B21: ='02_Roadmap'!H9 | C21: ='02_Roadmap'!E9 | D21: ='02_Roadmap'!F9
A22: ='02_Roadmap'!B10 | B22: ='02_Roadmap'!H10 | C22: ='02_Roadmap'!E10 | D22: ='02_Roadmap'!F10
A23: ='02_Roadmap'!B11 | B23: ='02_Roadmap'!H11 | C23: ='02_Roadmap'!E11 | D23: ='02_Roadmap'!F11
A24: ='02_Roadmap'!B12 | B24: ='02_Roadmap'!H12 | C24: ='02_Roadmap'!E12 | D24: ='02_Roadmap'!F12
A25: ='02_Roadmap'!B13 | B25: ='02_Roadmap'!H13 | C25: ='02_Roadmap'!E13 | D25: ='02_Roadmap'!F13
A26: ='02_Roadmap'!B14 | B26: ='02_Roadmap'!H14 | C26: ='02_Roadmap'!E14 | D26: ='02_Roadmap'!F14
A27: ='02_Roadmap'!B15 | B27: ='02_Roadmap'!H15 | C27: ='02_Roadmap'!E15 | D27: ='02_Roadmap'!F15
A28: ='02_Roadmap'!B16 | B28: ='02_Roadmap'!H16 | C28: ='02_Roadmap'!E16 | D28: ='02_Roadmap'!F16

Sheet 06_Decisions_Log
A1: Decisions Log
A2: Record key decisions so the project stays coherent over time.
A4: Decision ID | B4: Date | C4: Decision | D4: Rationale | E4: Owner | F4: Status | G4: Impacted Components | H4: Links/Notes
